termate/__init__.py
termate/const.py
termate/convert.py
termate/convert2lemon.py
termate/convert2rdf.py
termate/convert2skos.py
termate/convert_060.py
termate/convert_gsheets.py
termate/importskos.py
termate/lemonobjects.py
termate/models.py
termate/profiles.py
termate/termate.py
termate/types.py
termate/utils.py
termate/validator.vocpub.ttl
termate/vocab.py
termate-0.1.13.dist-info/AUTHORS.rst
termate-0.1.13.dist-info/LICENSE
termate-0.1.13.dist-info/METADATA
termate-0.1.13.dist-info/WHEEL
termate-0.1.13.dist-info/entry_points.txt
termate-0.1.13.dist-info/top_level.txt
termate-0.1.13.dist-info/RECORD
