Metadata-Version: 2.1
Name: termate
Version: 0.1.13
Summary: Package for terminology management with TermBase eXchange (TBX)
Home-page: https://github.com/DeNederlandscheBank/termate
Author: Willem Jan Willemse
Author-email: w.j.willemse@dnb.nl
License: MIT license
Keywords: termate
Classifier: Development Status :: 2 - Pre-Alpha
Classifier: Intended Audience :: Developers
Classifier: License :: OSI Approved :: MIT License
Classifier: Natural Language :: English
Classifier: Programming Language :: Python :: 3
Classifier: Programming Language :: Python :: 3.8
Classifier: Programming Language :: Python :: 3.9
Requires-Python: >=3.8
License-File: LICENSE
License-File: AUTHORS.rst
Requires-Dist: Click (>=7.0)
Requires-Dist: xlsxwriter
Requires-Dist: rdflib
Requires-Dist: iribaker
Requires-Dist: lxml
Requires-Dist: regex
